OracleSaaSApiPy/__init__.py
OracleSaaSApiPy/api.py
OracleSaaSApiPy/constants.py
OracleSaaSApiPy/utils.py
OracleSaaSApiPy-1.0.0.2.dist-info/LICENSE
OracleSaaSApiPy-1.0.0.2.dist-info/METADATA
OracleSaaSApiPy-1.0.0.2.dist-info/WHEEL
OracleSaaSApiPy-1.0.0.2.dist-info/top_level.txt
OracleSaaSApiPy-1.0.0.2.dist-info/RECORD
