Metadata-Version: 2.1
Name: OracleSaaSApiPy
Version: 1.0.0.2
Summary: An API wrapper for Oracle SaaS Webservice APIs
Home-page: https://github.com/pratik-m/OracleERPIntegrationServiceWrapper
Author: Pratik Munot
License: UNKNOWN
Platform: UNKNOWN
Classifier: Programming Language :: Python :: 3
Classifier: License :: OSI Approved :: MIT License
Classifier: Operating System :: OS Independent
Requires-Python: >=3.6
Requires-Dist: requests
